[
  {
    "company_logo": "https://camo.githubusercontent.com/56e71e3403b2c78b63007bf8f542f7b06c71f95542ae7154fe40f6a8b6b9e8a1/68747470733a2f2f63646e2e66732e746561636861626c6563646e2e636f6d2f72355937716a6271543036476a4d533451413057",
    "banner_img": "https://d15shllkswkct0.cloudfront.net/wp-content/blogs.dir/1/files/2019/10/67486615_896681964048795_7876402440935833600_n-768x337.png",
    "company_title": "Finally, A Modern Content Management System",
    "company_para": "Contentstack brings business and technology teams together to deliver personalized, omnichannel digital experiences.",
    "company_favIcon": "https://www.contentstack.com/favicon.ico",
    "socialLinks": {
      "twitter": "https://twitter.com/contentstack",
      "linkedin": "https://www.linkedin.com/company/contentstack",
      "facebook": "https://www.facebook.com/contentstack",
      "youtube": "https://www.youtube.com/contentstack",
      "github": "https://github.com/contentstack"
    }
  }
]
